catmouse
