Metadata-Version: 2.1
Name: catmouse
Version: 0.0.5
Summary: Mouse Logger for Science!
Home-page: https://github.com/Tsangares/cat_mouse
Author: William Wyatt
Author-email: tsangares@gmail.com
License: UNKNOWN
Platform: UNKNOWN
Classifier: Programming Language :: Python :: 3
Classifier: License :: OSI Approved :: MIT License
